wafl/__init__.py
wafl/__main__.py
wafl/command_line.py
wafl/config.py
wafl/exceptions.py
wafl/run.py
wafl/testcases.py
wafl/text_utils.py
wafl/variables.py
wafl/answerer/__init__.py
wafl/answerer/answerer_implementation.py
wafl/answerer/dialogue_answerer.py
wafl/answerer/entailer.py
wafl/answerer/rule_maker.py
wafl/connectors/__init__.py
wafl/connectors/base_llm_connector.py
wafl/connectors/prompt_template.py
wafl/connectors/utils.py
wafl/connectors/clients/__init__.py
wafl/connectors/clients/entailer_client.py
wafl/connectors/clients/information_client.py
wafl/connectors/clients/llm_chat_client.py
wafl/connectors/factories/__init__.py
wafl/connectors/factories/entailer_connector_factory.py
wafl/connectors/factories/llm_connector_factory.py
wafl/connectors/factories/sentence_embedder_connector_factory.py
wafl/connectors/factories/speaker_connector_factory.py
wafl/connectors/factories/whisper_connector_factory.py
wafl/connectors/remote/__init__.py
wafl/connectors/remote/remote_configuration_connector.py
wafl/connectors/remote/remote_entailer_connector.py
wafl/connectors/remote/remote_llm_connector.py
wafl/connectors/remote/remote_sentence_embedder_connector.py
wafl/connectors/remote/remote_speaker_connector.py
wafl/connectors/remote/remote_whisper_connector.py
wafl/data_objects/__init__.py
wafl/data_objects/dataclasses.py
wafl/data_objects/facts.py
wafl/data_objects/rules.py
wafl/events/BaseEventCreator.py
wafl/events/__init__.py
wafl/events/answerer_creator.py
wafl/events/conversation_events.py
wafl/events/conversational_memory.py
wafl/events/events_from_function_list.py
wafl/events/events_from_module_name.py
wafl/events/narrator.py
wafl/events/suppress_huggingface_logger.py
wafl/events/task_memory.py
wafl/events/utils.py
wafl/frontend/index.html
wafl/frontend/logo.png
wafl/frontend/selector.html
wafl/frontend/wafl.css
wafl/frontend/wafl.js
wafl/handlers/__init__.py
wafl/handlers/conversation_handler.py
wafl/handlers/generated_event_handler.py
wafl-0.1.4.dist-info/METADATA
wafl-0.1.4.dist-info/WHEEL
wafl-0.1.4.dist-info/entry_points.txt
wafl-0.1.4.dist-info/top_level.txt
wafl-0.1.4.dist-info/RECORD
