Metadata-Version: 2.1
Name: wafl
Version: 0.1.4
Summary: A hybrid chatbot.
Home-page: http://github.com/fractalego/wafl
Author: Alberto Cetoli
Author-email: alberto@fractalego.io
Classifier: License :: OSI Approved :: MIT License
Requires-Dist: flask[async] ==3.0.3
Requires-Dist: flask-cors ==4.0.1
Requires-Dist: nltk ==3.8.1
Requires-Dist: sklearn ==0.0
Requires-Dist: python-Levenshtein ==0.25.1
Requires-Dist: fuzzywuzzy ==0.18.0
Requires-Dist: PyAudio ==0.2.14
Requires-Dist: num2words ==0.5.13
Requires-Dist: word2number ==1.1
Requires-Dist: aiohttp ==3.9.5
Requires-Dist: werkzeug ==3.0.3
Requires-Dist: sphinx ==7.4.6
Requires-Dist: sphinx-rtd-theme ==2.0.0
Requires-Dist: g2p-en ==2.1.0
Requires-Dist: pyyaml ==6.0.1
Requires-Dist: joblib ==1.4.2
Requires-Dist: pymupdf ==1.24.7
